fei.ppds-1.2.1-py3.8-nspkg.pth
fei/ppds/__init__.py
fei/ppds/sync.py
fei.ppds-1.2.1.dist-info/METADATA
fei.ppds-1.2.1.dist-info/WHEEL
fei.ppds-1.2.1.dist-info/namespace_packages.txt
fei.ppds-1.2.1.dist-info/top_level.txt
fei.ppds-1.2.1.dist-info/RECORD
