Metadata-Version: 2.1
Name: fei.ppds
Version: 1.2.1
Summary: Customized synchronization classes
Home-page: https://github.com/Programator2/ppds
License: Unlicense
Platform: UNKNOWN
Classifier: Topic :: Software Development :: Libraries :: Python Modules
Classifier: Programming Language :: Python
Classifier: Programming Language :: Python :: 3
